SimonControl.v
//==============================================================================
// Control Module for Simon Project
//==============================================================================

module SimonControl(
	// External Inputs
	input        clk,           // Clock
	input        rst,           // Reset

	// Datapath Inputs
	input        valid_input,
	input 	     valid_repeat,
	input        seq_remain,

	// Datapath Control Outputs
	output reg   clear_i,
	output reg   increment_n,
	output reg   input_led_pattern,
	output reg   increment_i,
	output reg   write_pattern,

	// External Outputs
	output reg [2:0] mode_leds
);

	// Declare Local Vars Here
	reg [1:0] state;
	reg [1:0] next_state;

	// LED Light Parameters
	localparam LED_MODE_INPUT    = 3'b001;
	localparam LED_MODE_PLAYBACK = 3'b010;
	localparam LED_MODE_REPEAT   = 3'b100;
	localparam LED_MODE_DONE     = 3'b111;

	// Declare State Names Here
	localparam STATE_INPUT = 2'd0;
	localparam STATE_PLAYBACK = 2'd1;
	localparam STATE_REPEAT = 2'd2;
	localparam STATE_DONE = 2'd3;

	// Next State Combinational Logic
	always @( * ) begin
		// Write your Next State Logic Here
		next_state = state;

		case (state)
			STATE_INPUT: begin
				if (valid_input) begin
					next_state = STATE_PLAYBACK;
				end
				else begin
					next_state = STATE_INPUT;
				end
			end

			STATE_PLAYBACK: begin
				if (!seq_remain) begin
					next_state = STATE_REPEAT;
				end
				else begin
					next_state = STATE_PLAYBACK;
				end
			end

			STATE_REPEAT: begin
				if (valid_repeat) begin
					if (seq_remain) begin
						next_state = STATE_REPEAT;
					end
					else begin
						next_state = STATE_INPUT;
					end
				end
				else begin
					next_state = STATE_DONE;
				end
			end

			STATE_DONE: begin
				// next_state = STATE_DONE;
			end
		endcase
	end

	// Output Combinational Logic
	always @( * ) begin
		clear_i <= (state == STATE_INPUT && valid_input) || 
					(state == STATE_PLAYBACK && !seq_remain) || 
					(state == STATE_REPEAT && !valid_repeat) || 
					(state == STATE_DONE && !seq_remain);
		increment_i <= ((state == STATE_PLAYBACK) && seq_remain) || 
						((state == STATE_REPEAT) && valid_repeat) || 
						(state == STATE_DONE && seq_remain);
		increment_n <= (state == STATE_INPUT && valid_input);
		input_led_pattern <= (state == STATE_INPUT) || 
							(state == STATE_REPEAT);
		write_pattern <= (state == STATE_INPUT && valid_input);
	
		case (state)
			STATE_INPUT: begin
				mode_leds <= LED_MODE_INPUT;
			end

			STATE_PLAYBACK: begin
				mode_leds <= LED_MODE_PLAYBACK;
			end

			STATE_REPEAT: begin
				mode_leds <= LED_MODE_REPEAT;
			end

			STATE_DONE: begin
				mode_leds <= LED_MODE_DONE;
			end
		endcase 
	end

	// State Update Sequential Logic
	always @(posedge clk) begin
		if (rst) begin
			// Update state to reset state
			state <= STATE_INPUT;
		end
		else begin
			// Update state to next state
			state <= next_state;
		end
	end
endmodule

SimonControl.t.v
//===============================================================================
// Testbench Module for Simon Controller
//===============================================================================
`timescale 1ns/100ps

`include "SimonControl.v"

// Print an error message (MSG) if value ONE is not equal
// to value TWO.
`define ASSERT_EQ(ONE, TWO, MSG)               \
	begin                                      \
		if ((ONE) !== (TWO)) begin             \
			$display("\t[FAILURE]:%s", (MSG)); \
		end                                    \
	end #0

// Set the variable VAR to the value VALUE, printing a notification
// to the screen indicating the variable's update.
// The setting of the variable is preceeded and followed by
// a 1-timestep delay.
`define SET(VAR, VALUE) $display("Setting %s to %s...", "VAR", "VALUE"); #1; VAR = (VALUE); #1

// Cycle the clock up and then down, simulating
// a button press.
`define CLOCK $display("Pressing uclk..."); #1; clk = 1; #1; clk = 0; #1

module SimonControlTest;

	// Local Vars
	reg clk = 0;
	reg rst = 0;
	// More vars here...
	reg valid_input = 0;
	reg valid_repeat = 0;
	reg seq_remain = 0;
	wire clear_i;
	wire increment_n;
	wire increment_i;
	wire input_led_pattern;
	wire [2:0] mode_leds;
	wire write_pattern;

	// LED Light Parameters
	localparam LED_MODE_INPUT    = 3'b001;
	localparam LED_MODE_PLAYBACK = 3'b010;
	localparam LED_MODE_REPEAT   = 3'b100;
	localparam LED_MODE_DONE     = 3'b111;

	// VCD Dump
	initial begin
		$dumpfile("SimonControlTest.vcd");
		$dumpvars;
	end

	// Simon Control Module
	SimonControl ctrl(
		.clk (clk),
		.rst (rst),
		// More ports here...
		.valid_input (valid_input),
		.valid_repeat (valid_repeat),
		.seq_remain (seq_remain),
		.clear_i (clear_i),
		.increment_n (increment_n),
		.increment_i (increment_i),
		.input_led_pattern (input_led_pattern),
		.write_pattern(write_pattern),
		.mode_leds (mode_leds)
	);

	// Main Test Logic
	initial begin
		// Reset the game
		`SET(rst, 1);
		`CLOCK;
		`SET(rst, 0);

		// Your Test Logic Here
		`ASSERT_EQ(mode_leds, 3'b001, "Mode should be input mode (001).");

		`SET(valid_input, 0);
		`CLOCK;

		`ASSERT_EQ(clear_i, 0, "i should not be cleared.");
		`ASSERT_EQ(increment_n, 0, "n should not be incremented.");
		`ASSERT_EQ(mode_leds, 3'b001, "Mode should still be input mode (001) because pattern is invalid for level.");
		`ASSERT_EQ(input_led_pattern, 1, "pattern_led should show user input.");

		`SET(valid_input, 1);
		`ASSERT_EQ(increment_n, 1, "n should be incremented because a valid pattern was inputed.");
		
		`CLOCK;

		`ASSERT_EQ(clear_i, 1, "i should be cleared because switched to new state PLAYBACK.");
		`ASSERT_EQ(mode_leds, 3'b010, "Mode should be switched to Playback.");
		`ASSERT_EQ(input_led_pattern, 0, "pattern led should show stored patterns.");
		
		`SET(seq_remain, 1);
		`CLOCK;

		`ASSERT_EQ(clear_i, 0, "i should not be cleared because there is sequence remaining in PLAYBACK.");
		`ASSERT_EQ(increment_n, 0, "n should not be incremented in PLAYBACK.");
		`ASSERT_EQ(mode_leds, 3'b010, "Mode should be PLAYBACK.");
		`ASSERT_EQ(input_led_pattern, 0, "pattern led should show stored patterns.");

		`SET(seq_remain, 0);
		`CLOCK;

		`ASSERT_EQ(clear_i, 1, "i should be cleared because entering REPEAT.");
		`ASSERT_EQ(increment_n, 0, "n should not be incremented in PLAYBACK.");
		`ASSERT_EQ(mode_leds, 3'b100, "Mode should be REPEAT.");
		`ASSERT_EQ(input_led_pattern, 1, "pattern led should show user input.");

		`SET(seq_remain, 1);
		`SET(valid_repeat, 1);
		`CLOCK;

		`ASSERT_EQ(mode_leds, 3'b100, "Should still be in repeat because there is remaining pattern to guess.");

		`SET(seq_remain, 0);
		`SET(valid_input, 0);
		`CLOCK;

		`ASSERT_EQ(mode_leds, 3'b001, "Finished guessing sequence and should return to INPUT.");
		`ASSERT_EQ(increment_n, 0, "n should not be incremented when just returned to INPUT state.");
		`ASSERT_EQ(clear_i, 0, "i should not be cleared");
		`ASSERT_EQ(input_led_pattern, 1, "pattern led should show user input.");

		$finish;
	end

endmodule

SimonControlTest.vcd
$date
	Mon Dec  2 13:56:29 2019
$end
$version
	Icarus Verilog
$end
$timescale
	100ps
$end
$scope module SimonControlTest $end
$var wire 1 ! write_pattern $end
$var wire 3 " mode_leds [2:0] $end
$var wire 1 # input_led_pattern $end
$var wire 1 $ increment_n $end
$var wire 1 % increment_i $end
$var wire 1 & clear_i $end
$var reg 1 ' clk $end
$var reg 1 ( rst $end
$var reg 1 ) seq_remain $end
$var reg 1 * valid_input $end
$var reg 1 + valid_repeat $end
$scope module ctrl $end
$var wire 1 ' clk $end
$var wire 1 ( rst $end
$var wire 1 ) seq_remain $end
$var wire 1 * valid_input $end
$var wire 1 + valid_repeat $end
$var reg 1 & clear_i $end
$var reg 1 % increment_i $end
$var reg 1 $ increment_n $end
$var reg 1 # input_led_pattern $end
$var reg 3 , mode_leds [2:0] $end
$var reg 2 - next_state [1:0] $end
$var reg 2 . state [1:0] $end
$var reg 1 ! write_pattern $end
$upscope $end
$upscope $end
$enddefinitions $end
#0
$dumpvars
bx .
bx -
bx ,
0+
0*
0)
0(
0'
x&
x%
0$
x#
bx "
0!
$end
#10
1(
#30
b1 "
b1 ,
1#
0%
0&
b0 -
b0 .
1'
#40
0'
#60
0(
#100
1'
#110
0'
#130
1!
1$
1&
b1 -
1*
#150
b10 "
b10 ,
0!
0#
0$
b10 -
b1 .
1'
#160
0'
#180
1%
0&
b1 -
1)
#200
1'
#210
0'
#230
0%
1&
b10 -
0)
#250
b100 "
b100 ,
1#
b11 -
b10 .
1'
#260
0'
#280
b11 -
1)
#300
1%
0&
b10 -
1+
#320
1'
#330
0'
#350
b0 -
0)
#370
b0 -
0*
#390
b1 "
b1 ,
0%
b0 .
1'
